{
  "scannedAt": "2026-03-21T10:16:40.158Z",
  "keywords": {
    "住宅補助金": {
      "resultCount": 0,
      "totalScore": 0,
      "avgScore": 0,
      "topPosts": []
    },
    "マイホーム": {
      "resultCount": 0,
      "totalScore": 0,
      "avgScore": 0,
      "topPosts": []
    },
    "住宅ローン": {
      "resultCount": 2,
      "totalScore": 13,
      "avgScore": 6.5,
      "topPosts": [
        {
          "id": "18179182480373067",
          "text": "住宅ローン減税、また変わるらしい。\n\n自分が建てた2年前もギリギリ制度変わる前に間に合わせようって焦ってたのに、結局また変わるんかよって感じ。\n\nタイミングで何百万も変わるのに、その「タイミング」が全然読めない。\n\n家建てるって、運ゲーの要素強すぎると思う。みんなはどのタイミングで決断した？",
          "username": "custom_housing_hikaku",
          "timestamp": "2026-02-25T12:39:10+0000",
          "permalink": "https://www.threads.com/@custom_housing_hikaku/post/DVLmKaNkZK6",
          "insights": {
            "views": 2878,
            "likes": 5,
            "replies": 2,
            "reposts": 0,
            "quotes": 0
          },
          "score": 13
        },
        {
          "id": "18080516399035663",
          "text": "固定資産税の見直し、地味に気になってる。\n\n住宅ローンの返済額は計算するのに、毎年かかる税金って後回しにしがちなんだよね。\n\nローン返済中に「こんなにかかるの？」ってなった人、相談の中でもちょいちょい出てくる。\n建てる前にちゃんと試算しておきたいやつだわ。",
          "username": "custom_housing_hikaku",
          "timestamp": "2026-02-27T05:44:06+0000",
          "permalink": "https://www.threads.com/@custom_housing_hikaku/post/DVQAQG6jo3E",
          "insights": {
            "views": 398,
            "likes": 0,
            "replies": 0,
            "reposts": 0,
            "quotes": 0
          },
          "score": 0
        }
      ]
    },
    "家づくり": {
      "resultCount": 9,
      "totalScore": 26,
      "avgScore": 5.2,
      "topPosts": [
        {
          "id": "18133012798502152",
          "text": "春の引っ越しに間に合わせたくて、土地決めを急ぐ人多いと思うんだけど、自分もそれで失敗した。焦ると後悔しやすいぞ。\n\n家づくり",
          "username": "custom_housing_hikaku",
          "timestamp": "2026-02-23T11:59:31+0000",
          "permalink": "https://www.threads.com/@custom_housing_hikaku/post/DVGYCPBlt3l",
          "insights": {
            "views": 964,
            "likes": 2,
            "replies": 1,
            "reposts": 0,
            "quotes": 0
          },
          "score": 6
        },
        {
          "id": "18089419859123743",
          "text": "間取り決めを嫁に全部任せて、後から「ここ使いづらくない？」って言ったことめっちゃ後悔してる。一緒に決めてりゃよかった。\n\n家づくり",
          "username": "custom_housing_hikaku",
          "timestamp": "2026-02-23T10:37:55+0000",
          "permalink": "https://www.threads.com/@custom_housing_hikaku/post/DVGOskPDvMM",
          "insights": {
            "views": 934,
            "likes": 2,
            "replies": 1,
            "reposts": 0,
            "quotes": 0
          },
          "score": 6
        },
        {
          "id": "17896685115400248",
          "text": "リモートワーク定着で郊外増えるってニュース見たけど、通勤なしになるとマジで家選びの自由度変わるんだな。\n\n三重県 #家づくり",
          "username": "custom_housing_hikaku",
          "timestamp": "2026-02-23T12:01:05+0000",
          "permalink": "https://www.threads.com/@custom_housing_hikaku/post/DVGYNqsFozR",
          "insights": {
            "views": 273,
            "likes": 1,
            "replies": 1,
            "reposts": 0,
            "quotes": 0
          },
          "score": 5
        }
      ]
    },
    "土地探し": {
      "resultCount": 4,
      "totalScore": 8,
      "avgScore": 2,
      "topPosts": [
        {
          "id": "17877469524485298",
          "text": "三重で土地探してる人に朗報。\n\nうちのサイト、エリア別の土地相場ページ作ったんだけど、これがめちゃくちゃ使えると思ってる。\n\n津と四日市でこんなに違うんだとか、松阪ならこのくらいで探せるんだとか、比べながら見られる。\n「どのエリアにするか決めてない」段階の人こそ、先に見てほしい。\n\nプロフィールにリンクあるよ。",
          "username": "custom_housing_hikaku",
          "timestamp": "2026-02-28T13:30:34+0000",
          "permalink": "https://www.threads.com/@custom_housing_hikaku/post/DVTabmEEY4Y",
          "insights": {
            "views": 57,
            "likes": 0,
            "replies": 1,
            "reposts": 0,
            "quotes": 0
          },
          "score": 4
        },
        {
          "id": "18044765177733474",
          "text": "土地探しの時、こういうサイトが欲しかった。\n\n三重県の注文住宅情報サイト作ってるんだけど、エリアごとに学区情報とか住みやすさをまとめたページを追加した。\n\n土地探してた頃、これが全然ネット上になくて困ったんだよね。\nリンクはプロフィールに貼ってあるから見てみて。",
          "username": "custom_housing_hikaku",
          "timestamp": "2026-02-24T22:23:00+0000",
          "permalink": "https://www.threads.com/@custom_housing_hikaku/post/DVKELwzFGsJ",
          "insights": {
            "views": 264,
            "likes": 0,
            "replies": 1,
            "reposts": 0,
            "quotes": 0
          },
          "score": 4
        },
        {
          "id": "18090978671515031",
          "text": "「三重で2,500万で建てたい」って相談、すごく多い。\n\nただ土地代によって、建物に使える金額が全然変わる。\n駅の近くで土地探してたら、建物予算が1,500万切ってた、なんてことも普通にある。\n\n予算って「総額」で考えないと後でしんどくなる。\n💡",
          "username": "custom_housing_hikaku",
          "timestamp": "2026-03-18T05:56:50+0000",
          "permalink": "https://www.threads.com/@custom_housing_hikaku/post/DWA80BJFHgp",
          "insights": {
            "views": 381,
            "likes": 0,
            "replies": 0,
            "reposts": 0,
            "quotes": 0
          },
          "score": 0
        }
      ]
    },
    "新築": {
      "resultCount": 6,
      "totalScore": 194,
      "avgScore": 38.8,
      "topPosts": [
        {
          "id": "17868796203563607",
          "text": "コンセント、ケチるな。\n\n新築なのに延長コードが床を這ってる。\n自分の家、まさにこれ。\n\n後から増設しようとしたら「壁壊すんで15万です」って言われた。\n追加工事で頼んどきゃ数千円だったのに。\n\nみんなはコンセント足りてる？",
          "username": "custom_housing_hikaku",
          "timestamp": "2026-02-24T03:19:17+0000",
          "permalink": "https://www.threads.com/@custom_housing_hikaku/post/DVIBS8wjfje",
          "insights": {
            "views": 13399,
            "likes": 45,
            "replies": 37,
            "reposts": 0,
            "quotes": 0
          },
          "score": 193
        },
        {
          "id": "18055467242438452",
          "text": "補助金、知ってる人と知らない人で100万以上差がつく。\n\n今年も新築向けの補助金が出てて、うまく使えた人は総額100万超えてる。\nでも申請のタイミングを間違えると、条件満たしてても受け取れないことがある。\n\nせっかく建てるなら、ローン組む前に確認しておいた方がいいやつ。\n📍",
          "username": "custom_housing_hikaku",
          "timestamp": "2026-03-06T10:24:56+0000",
          "permalink": "https://www.threads.com/@custom_housing_hikaku/post/DVih9KeETf9",
          "insights": {
            "views": 562,
            "likes": 1,
            "replies": 0,
            "reposts": 0,
            "quotes": 0
          },
          "score": 1
        },
        {
          "id": "18381861112092972",
          "text": "近所付き合い、新築時点では濃いのがデフォなんだよね。あと土地を後から買う場合、既存住民からの視線も結構重いやつだわ。",
          "username": "custom_housing_hikaku",
          "timestamp": "2026-03-20T16:41:47+0000",
          "permalink": "https://www.threads.com/@custom_housing_hikaku/post/DWHQNlvGBly",
          "insights": {
            "views": 0,
            "likes": 0,
            "replies": 0,
            "reposts": 0,
            "quotes": 0
          },
          "score": 0
        }
      ]
    },
    "三重県": {
      "resultCount": 5,
      "totalScore": 30,
      "avgScore": 6,
      "topPosts": [
        {
          "id": "17872932507538897",
          "text": "四日市に住んでみて思うけど、記事とか見ると「便利で安い穴場」みたいに書かれてるやん。でも実際のとこ名古屋までの通勤ラッシュはまじきついし、坪単価も下がってきてるんだよね。\n\nhttps://research.chuumon-soudan.com/knowledge/mie-livability/\n\n三重県 #四日市",
          "username": "custom_housing_hikaku",
          "timestamp": "2026-02-22T14:40:14+0000",
          "permalink": "https://www.threads.com/@custom_housing_hikaku/post/DVEFodcDiM3",
          "insights": {
            "views": 205,
            "likes": 0,
            "replies": 3,
            "reposts": 0,
            "quotes": 0
          },
          "score": 12
        },
        {
          "id": "18079185776065216",
          "text": "補助金、知らないと本当にもったいない。\n\n三重県で家を建てる相談者に伝えると、ほとんどの人が「そんな制度あったんですか」って反応する。\n\n国の補助金だけじゃなくて、市単位で使える制度もあるから、どこで建てるかで受け取れる額が全然変わってくる。\n\n「申請のタイミングを逃した」って後悔、よく聞くから早めに調べとくのが吉。",
          "username": "custom_housing_hikaku",
          "timestamp": "2026-02-28T03:45:48+0000",
          "permalink": "https://www.threads.com/@custom_housing_hikaku/post/DVSXgiGDbQO",
          "insights": {
            "views": 360,
            "likes": 1,
            "replies": 1,
            "reposts": 0,
            "quotes": 0
          },
          "score": 5
        },
        {
          "id": "17896685115400248",
          "text": "リモートワーク定着で郊外増えるってニュース見たけど、通勤なしになるとマジで家選びの自由度変わるんだな。\n\n三重県 #家づくり",
          "username": "custom_housing_hikaku",
          "timestamp": "2026-02-23T12:01:05+0000",
          "permalink": "https://www.threads.com/@custom_housing_hikaku/post/DVGYNqsFozR",
          "insights": {
            "views": 273,
            "likes": 1,
            "replies": 1,
            "reposts": 0,
            "quotes": 0
          },
          "score": 5
        }
      ]
    },
    "いなべ": {
      "resultCount": 2,
      "totalScore": 27,
      "avgScore": 13.5,
      "topPosts": [
        {
          "id": "18122466883583761",
          "text": "いなべ市で建てた人、総額2,500万円台で収まったって人が結構いる。🔑\n\n土地が安いのと、移住の補助金が使えるのが大きくて、三重の北の方で一番予算に余裕持って建てられたって声をよく聞く。\n\nみんなはいなべ、候補に入ってた？",
          "username": "custom_housing_hikaku",
          "timestamp": "2026-03-10T10:29:42+0000",
          "permalink": "https://www.threads.com/@custom_housing_hikaku/post/DVs1rtmkTsi",
          "insights": {
            "views": 5684,
            "likes": 7,
            "replies": 5,
            "reposts": 0,
            "quotes": 0
          },
          "score": 27
        },
        {
          "id": "17879074077531206",
          "text": "その通り。いなべは土地が割安だから、同じ予算でも名古屋近い地域より広い家建てられるって相談めちゃ多いよね。補助金も地味だけど効くから、予算重視の人には穴場になってる。",
          "username": "custom_housing_hikaku",
          "timestamp": "2026-03-16T09:54:36+0000",
          "permalink": "https://www.threads.com/@custom_housing_hikaku/post/DV8Ob1VkZlp",
          "insights": {
            "views": 4,
            "likes": 0,
            "replies": 0,
            "reposts": 0,
            "quotes": 0
          },
          "score": 0
        }
      ]
    },
    "住宅展示場 春": {
      "resultCount": 0,
      "totalScore": 0,
      "avgScore": 0,
      "topPosts": []
    },
    "引っ越し 新居": {
      "resultCount": 0,
      "totalScore": 0,
      "avgScore": 0,
      "topPosts": []
    }
  }
}